{
	"name": "Parquet1",
	"properties": {
		"linkedServiceName": {
			"referenceName": "AzureBlobStorage1",
			"type": "LinkedServiceReference"
		},
		"annotations": [],
		"type": "Parquet",
		"typeProperties": {
			"location": {
				"type": "AzureBlobStorageLocation",
				"fileName": "part-00000-tid-1418677109379703799-6c0f9598-8c8f-4d58-b291-3dc815167897-228-1-c000.snappy.parquet",
				"container": "gold"
			},
			"compressionCodec": "snappy"
		},
		"schema": []
	},
	"type": "Microsoft.DataFactory/factories/datasets"
}